pre_v7_unix_summarizer/__init__.py
pre_v7_unix_summarizer/main.py
pre_v7_unix_summarizer/prompts.py
pre_v7_unix_summarizer-2025.12.21164816.dist-info/METADATA
pre_v7_unix_summarizer-2025.12.21164816.dist-info/WHEEL
pre_v7_unix_summarizer-2025.12.21164816.dist-info/top_level.txt
pre_v7_unix_summarizer-2025.12.21164816.dist-info/RECORD
