Metadata-Version: 2.4
Name: pre-v7-unix-summarizer
Version: 2025.12.21164816
Summary: A new package that processes text input related to early Unix history (pre-V7) and returns structured, verified summaries using pattern matching and LLM interactions. It takes user-provided text (e.g.
Author-email: pre-v7-unix-summarizer <hi@eugene.plus>
License: MIT
Project-URL: Homepage, https://github.com/chigwell/pre-v7-unix-summarizer
Requires-Python: >=3.9
Requires-Dist: langchain-llm7>=0.0.0
Requires-Dist: llmatch-messages>=0.0.0
Requires-Dist: langchain-core>=0.3.0
